darkon/__init__.py
darkon/log.py
darkon/gradcam/__init__.py
darkon/gradcam/candidate_ops.py
darkon/gradcam/gradcam.py
darkon/gradcam/guided_grad.py
darkon/influence/__init__.py
darkon/influence/feeder.py
darkon/influence/influence.py
darkon-0.0.6.dist-info/DESCRIPTION.rst
darkon-0.0.6.dist-info/METADATA
darkon-0.0.6.dist-info/RECORD
darkon-0.0.6.dist-info/WHEEL
darkon-0.0.6.dist-info/metadata.json
darkon-0.0.6.dist-info/top_level.txt
test/__init__.py
test/test_gradcam.py
test/test_gradcam_dangling.py
test/test_gradcam_guided_backprop.py
test/test_gradcam_sequence.py
test/test_gradcam_util.py
test/test_influence.py
test/test_influence_dropout.py
test/test_influence_feeder.py
test/tf_util.py
