Metadata-Version: 2.0
Name: darkon
Version: 0.0.6
Summary: Performance hacking for your deep learning models
Home-page: https://github.com/darkonhub/darkon
Author: Neosapience, Inc.
Author-email: UNKNOWN
License: Apache License 2.0
Download-URL: https://github.com/darkonhub/darkon/tarball/v0.0.6
Keywords: AI,ML,DL,deep learning,machine learning,neural network,deep neural network,debug neural networks,performance hacking,tensorflow,tf
Platform: UNKNOWN
Classifier: Development Status :: 2 - Pre-Alpha
Classifier: Intended Audience :: Developers
Classifier: Intended Audience :: Science/Research
Classifier: License :: OSI Approved :: Apache Software License
Classifier: Programming Language :: Python :: 2
Classifier: Programming Language :: Python :: 2.7
Classifier: Programming Language :: Python :: 3
Classifier: Programming Language :: Python :: 3.6
Classifier: Topic :: Scientific/Engineering :: Artificial Intelligence
Classifier: Topic :: Software Development :: Debuggers
Classifier: Topic :: Software Development :: Libraries :: Python Modules
Requires-Dist: numpy
Requires-Dist: opencv-python
Requires-Dist: scikit-image
Requires-Dist: six
Provides-Extra: tensorflow
Requires-Dist: tensorflow (>=1.3); extra == 'tensorflow'
Provides-Extra: tensorflow-gpu
Requires-Dist: tensorflow-gpu (>=1.3); extra == 'tensorflow-gpu'
